localtileserver/__init__.py
localtileserver/__main__.py
localtileserver/_version.py
localtileserver/client.py
localtileserver/configure.py
localtileserver/examples.py
localtileserver/helpers.py
localtileserver/manager.py
localtileserver/report.py
localtileserver/utilities.py
localtileserver/validate.py
localtileserver/widgets.py
localtileserver/tiler/__init__.py
localtileserver/tiler/handler.py
localtileserver/tiler/palettes.py
localtileserver/tiler/utilities.py
localtileserver/tiler/data/.gitignore
localtileserver/tiler/data/__init__.py
localtileserver/tiler/data/aws_elevation_tiles_prod.xml
localtileserver/tiler/data/bahamas_rgb.tif
localtileserver/tiler/data/co_elevation_roi.tif
localtileserver/tiler/data/frmt_wms_arcgis_mapserver_tms.xml
localtileserver/tiler/data/frmt_wms_bluemarble_s3_tms.xml
localtileserver/tiler/data/frmt_wms_virtualearth.xml
localtileserver/tiler/data/landsat.tif
localtileserver/tiler/data/landsat7.tif
localtileserver/tiler/data/presidio.wkb
localtileserver/tiler/data/srtm90.tif
localtileserver/web/__init__.py
localtileserver/web/application.py
localtileserver/web/blueprint.py
localtileserver/web/rest.py
localtileserver/web/sentry.py
localtileserver/web/urls.py
localtileserver/web/utils.py
localtileserver/web/views.py
localtileserver/web/wsgi.py
localtileserver/web/static/js/cesium.js
localtileserver/web/static/styles/cesium.css
localtileserver/web/static/styles/snackbar.css
localtileserver/web/static/styles/style.css
localtileserver/web/templates/tileserver/404file.html
localtileserver/web/templates/tileserver/base.html
localtileserver/web/templates/tileserver/baseTileViewer.html
localtileserver/web/templates/tileserver/cesiumSplitViewer.html
localtileserver/web/templates/tileserver/cesiumViewer.html
localtileserver/web/templates/tileserver/splitForm.html
localtileserver/web/templates/tileserver/_include/cesium.html
localtileserver/web/templates/tileserver/_include/examples.html
localtileserver-0.10.7.dist-info/licenses/LICENSE
localtileserver-0.10.7.dist-info/METADATA
localtileserver-0.10.7.dist-info/WHEEL
localtileserver-0.10.7.dist-info/entry_points.txt
localtileserver-0.10.7.dist-info/top_level.txt
localtileserver-0.10.7.dist-info/RECORD
