Metadata-Version: 2.4
Name: localtileserver
Version: 0.10.7
Summary: Locally serve geospatial raster tiles in the Slippy Map standard.
Author-email: Bane Sullivan <hello@banesullivan.com>
Project-URL: Documentation, https://localtileserver.banesullivan.com
Project-URL: Bug Tracker, https://github.com/banesullivan/localtileserver/issues
Project-URL: Source Code, https://github.com/banesullivan/localtileserver
Classifier: Development Status :: 4 - Beta
Classifier: License :: OSI Approved :: MIT License
Classifier: Intended Audience :: Science/Research
Classifier: Topic :: Scientific/Engineering :: Information Analysis
Classifier: Operating System :: OS Independent
Classifier: Programming Language :: Python :: 3.10
Classifier: Programming Language :: Python :: 3.11
Classifier: Programming Language :: Python :: 3.12
Classifier: Programming Language :: Python :: 3.13
Requires-Python: >=3.10
License-File: LICENSE
Requires-Dist: click
Requires-Dist: flask<4,>=2.0.0
Requires-Dist: Flask-Caching
Requires-Dist: flask-cors
Requires-Dist: flask-restx>=1.3.0
Requires-Dist: rio-tiler
Requires-Dist: rio-cogeo
Requires-Dist: requests
Requires-Dist: server-thread
Requires-Dist: scooby
Requires-Dist: werkzeug
Provides-Extra: colormaps
Requires-Dist: matplotlib; extra == "colormaps"
Requires-Dist: cmocean; extra == "colormaps"
Requires-Dist: colorcet; extra == "colormaps"
Provides-Extra: jupyter
Requires-Dist: jupyter-server-proxy; extra == "jupyter"
Requires-Dist: ipyleaflet; extra == "jupyter"
Provides-Extra: helpers
Requires-Dist: shapely; extra == "helpers"
Dynamic: license-file
